asd21libraries/__init__.py
asd21libraries/seismic_functions.py
asd21libraries-1.0.7.dist-info/METADATA
asd21libraries-1.0.7.dist-info/WHEEL
asd21libraries-1.0.7.dist-info/top_level.txt
asd21libraries-1.0.7.dist-info/RECORD
