Metadata-Version: 2.1
Name: asd21libraries
Version: 1.0.7
Summary: Seismic processing functions
Author: Alexander S. Douglass
License: UW
